faker_cli/__init__.py
faker_cli/cli.py
faker_cli/parser.py
faker_cli/providers/base.py
faker_cli/providers/faker.py
faker_cli/providers/mimesis.py
faker_cli/templates.py
faker_cli/writer.py
faker_cli/writers/delta.py
faker_cli/writers/iceberg.py
faker_cli/writers/parquet.py
faker_cli-0.7.0.dist-info/LICENSE
faker_cli-0.7.0.dist-info/METADATA
faker_cli-0.7.0.dist-info/WHEEL
faker_cli-0.7.0.dist-info/entry_points.txt
faker_cli-0.7.0.dist-info/RECORD
