Metadata-Version: 2.1
Name: faker-cli
Version: 0.7.0
Summary: Command-line fake data generator
Author: Damon P. Cortesi
Author-email: d.lifehacker@gmail.com
Requires-Python: >=3.10,<4.0
Classifier: Programming Language :: Python :: 3
Classifier: Programming Language :: Python :: 3.10
Classifier: Programming Language :: Python :: 3.11
Classifier: Programming Language :: Python :: 3.12
Provides-Extra: delta
Provides-Extra: iceberg
Provides-Extra: parquet
Requires-Dist: click (>=8.1.3,<9.0.0)
Requires-Dist: deltalake (>=0.9.0,<0.10.0) ; extra == "delta"
Requires-Dist: faker (>=18.9.0,<19.0.0)
Requires-Dist: mimesis (>=17.0.0,<18.0.0)
Requires-Dist: numpy (<2)
Requires-Dist: pyarrow (>=14.0.2,<14.1.0) ; extra == "delta" or extra == "parquet"
Requires-Dist: pyiceberg[glue,pyarrow,sql-sqlite] (>=0.6.0,<0.7.0) ; extra == "iceberg"
Requires-Dist: setuptools (>=70.3.0,<71.0.0)
Requires-Dist: urllib3 (<2)
